{
  "color-1-elements-background": {
    "value": "#fffffe"
  },
  "color-1-elements-headline": {
    "value": "#272343"
  },
  "color-1-elements-paragraph": {
    "value": "#2d334a"
  },
  "color-1-elements-button": {
    "value": "#ffd803"
  },
  "color-1-elements-button-text": {
    "value": "#272343"
  },
  "color-1-illustration-stroke": {
    "value": "#272343"
  },
  "color-1-illustration-main": {
    "value": "#fffffe"
  },
  "color-1-illustration-highlight": {
    "value": "#ffd803"
  },
  "color-1-illustration-secondary": {
    "value": "#e3f6f5"
  },
  "color-1-illustration-tertiary": {
    "value": "#bae8e8"
  },
  "color-2-elements-background": {
    "value": "#e3f6f5"
  },
  "color-2-elements-headline": {
    "value": "#272343"
  },
  "color-2-elements-sub-headline": {
    "value": "#2d334a"
  },
  "color-2-elements-card-background": {
    "value": "#fffffe"
  },
  "color-2-elements-card-heading": {
    "value": "#272343"
  },
  "color-2-elements-card-paragraph": {
    "value": "#2d334a"
  },
  "color-2-icons-stroke": {
    "value": "#272343"
  },
  "color-2-icons-main": {
    "value": "#fffffe"
  },
  "color-2-icons-highlight": {
    "value": "#ffd803"
  },
  "color-2-icons-secondary": {
    "value": "#e3f6f5"
  },
  "color-2-icons-tertiary": {
    "value": "#bae8e8"
  },
  "color-3-background": {
    "value": "#fffffe"
  },
  "color-3-headline": {
    "value": "#272343"
  },
  "color-3-paragraph": {
    "value": "#2d334a"
  },
  "color-3-card-background": {
    "value": "#272343"
  },
  "color-3-card-headline": {
    "value": "#fffffe"
  },
  "color-3-card-paragraph": {
    "value": "#2d334a"
  },
  "color-3-card-tag-background": {
    "value": "#bae8e8"
  },
  "color-3-card-tag-text": {
    "value": "#272343"
  },
  "color-3-card-highlight": {
    "value": "#bae8e8"
  },
  "color-4-elements-background": {
    "value": "#e3f6f5"
  },
  "color-4-elements-headline": {
    "value": "#272343"
  },
  "color-4-elements-paragraph": {
    "value": "#2d334a"
  },
  "color-4-elements-link": {
    "value": "#272343"
  },
  "color-4-elements-card-backgroud": {
    "value": "#fffffe"
  },
  "color-4-elements-card-headline": {
    "value": "#272343"
  },
  "color-4-elements-card-paragraph": {
    "value": "#2d334a"
  },
  "color-4-newsletter-background": {
    "value": "#bae8e8"
  },
  "color-4-newsletter-form-input": {
    "value": "#fffffe"
  },
  "color-4-newsletter-label-&-placeholder": {
    "value": "#272343"
  },
  "color-4-newsletter-form-button": {
    "value": "#272343"
  },
  "color-4-newsletter-form-button-text": {
    "value": "#fffffe"
  },
  "color-5-elements-background": {
    "value": "#fffffe"
  },
  "color-5-elements-headline": {
    "value": "#272343"
  },
  "color-5-elements-paragraph": {
    "value": "#2d334a"
  },
  "color-5-elements-links": {
    "value": "#ffd803"
  }
}